CHANGES.txt
DEPENDENCES.txt
README.txt
setup.py
src/ng/__init__.py
src/ng.skin.dreambot.egg-info/PKG-INFO
src/ng.skin.dreambot.egg-info/SOURCES.txt
src/ng.skin.dreambot.egg-info/dependency_links.txt
src/ng.skin.dreambot.egg-info/namespace_packages.txt
src/ng.skin.dreambot.egg-info/not-zip-safe
src/ng.skin.dreambot.egg-info/requires.txt
src/ng.skin.dreambot.egg-info/top_level.txt
src/ng/skin/__init__.py
src/ng/skin/dreambot/__init__.py
src/ng/skin/dreambot/configure.zcml
src/ng/skin/dreambot/interfaces.py
src/ng/skin/dreambot/ng.skin.dreambot.txt
src/ng/skin/dreambot/remark.txt
src/ng/skin/dreambot/skeleton.pt
src/ng/skin/dreambot/style.css
src/ng/skin/dreambot/style_ie.css
src/ng/skin/dreambot/etc/ng.skin.dreambot-configure.zcml
src/ng/skin/dreambot/images/bottomlogo.png
src/ng/skin/dreambot/images/logo.gif
src/ng/skin/dreambot/images/logo.png
src/ng/skin/dreambot/images/toplogo.png
src/ng/skin/dreambot/main/__init__.py
src/ng/skin/dreambot/main/configure.zcml
src/ng/skin/dreambot/main/main.css
src/ng/skin/dreambot/main/main.pt
src/ng/skin/dreambot/product/__init__.py
src/ng/skin/dreambot/product/configure.zcml
src/ng/skin/dreambot/product/product.pt
src/ng/skin/dreambot/product/product.py